yldprolog/__init__.py
yldprolog/compiler.py
yldprolog/engine.py
yldprolog/errors.py
yldprolog/prologLexer.py
yldprolog/prologListener.py
yldprolog/prologParser.py
yldprolog/prologVisitor.py
yldprolog/yp_generator.py
yldprolog/yp_prolog_visitor.py
yldprolog-1.3.1.dist-info/METADATA
yldprolog-1.3.1.dist-info/WHEEL
yldprolog-1.3.1.dist-info/entry_points.txt
yldprolog-1.3.1.dist-info/top_level.txt
yldprolog-1.3.1.dist-info/RECORD
