Metadata-Version: 2.1
Name: yldprolog
Version: 1.3.1
Summary: A rewrite of Yield Prolog for Python
Home-page: https://github.com/timhemel/yldprolog
Author: Tim Hemel
Author-email: tim@securesoftware.nl
Keywords: prolog
Classifier: Programming Language :: Python :: 3
Classifier: License :: OSI Approved :: GNU Affero General Public License v3
Classifier: Operating System :: OS Independent
Requires-Python: >=3.6
Requires-Dist: antlr4-python3-runtime (==4.9.1)
Requires-Dist: Click
